tejd_build_tools/VERSION
tejd_build_tools/__init__.py
tejd_build_tools/te_version.py
tejd_build_tools/build_tools/__init__.py
tejd_build_tools/build_tools/build_ext.py
tejd_build_tools/build_tools/utils.py
tejd_build_tools/common/common.h
tejd_build_tools/common/nvtx.h
tejd_build_tools/common/util/cast.cu
tejd_build_tools/common/util/cuda_driver.cpp
tejd_build_tools/common/util/cuda_driver.h
tejd_build_tools/common/util/cuda_runtime.cpp
tejd_build_tools/common/util/cuda_runtime.h
tejd_build_tools/common/util/logging.h
tejd_build_tools/common/util/math.h
tejd_build_tools/common/util/rtc.cpp
tejd_build_tools/common/util/rtc.h
tejd_build_tools/common/util/string.h
tejd_build_tools/common/util/string_header.h.in
tejd_build_tools/common/util/system.cpp
tejd_build_tools/common/util/system.h
tejd_build_tools/common/util/vectorized_pointwise.h
tejd_build_tools/cudnn-frontend/.clang-format
tejd_build_tools/cudnn-frontend/.git
tejd_build_tools/cudnn-frontend/CMakeLists.txt
tejd_build_tools/cudnn-frontend/CONTRIBUTING.md
tejd_build_tools/cudnn-frontend/LICENSE.txt
tejd_build_tools/cudnn-frontend/README.FE.0.x.md
tejd_build_tools/cudnn-frontend/README.FE.1.0.md
tejd_build_tools/cudnn-frontend/README.md
tejd_build_tools/cudnn-frontend/pyproject.toml
tejd_build_tools/cudnn-frontend/requirements.txt
tejd_build_tools/cudnn-frontend/setup.py
tejd_build_tools/cudnn-frontend/cmake/cuDNN.cmake
tejd_build_tools/cudnn-frontend/docs/operations/Attention.md
tejd_build_tools/cudnn-frontend/docs/operations/Convolutions.md
tejd_build_tools/cudnn-frontend/docs/operations/Matmul.md
tejd_build_tools/cudnn-frontend/docs/operations/Normalizations.md
tejd_build_tools/cudnn-frontend/docs/operations/Pointwise.md
tejd_build_tools/cudnn-frontend/docs/operations/Resampling.md
tejd_build_tools/cudnn-frontend/include/cudnn_backend_base.h
tejd_build_tools/cudnn-frontend/include/cudnn_frontend.h
tejd_build_tools/cudnn-frontend/include/cudnn_frontend_ConvDesc.h
tejd_build_tools-1.7.0.dev4.dist-info/LICENSE
tejd_build_tools-1.7.0.dev4.dist-info/METADATA
tejd_build_tools-1.7.0.dev4.dist-info/WHEEL
tejd_build_tools-1.7.0.dev4.dist-info/top_level.txt
tejd_build_tools-1.7.0.dev4.dist-info/RECORD
