Metadata-Version: 2.1
Name: tejd-build-tools
Version: 1.7.0.dev4
Summary: Transformer acceleration library - Build Requirements
License-File: LICENSE
